crackhash/__init__.py
crackhash/browser.py
crackhash/cli.py
crackhash/core.py
crackhash/helpers.py
crackhash/scraper.py
crackhash-1.0.1.dist-info/DESCRIPTION.rst
crackhash-1.0.1.dist-info/METADATA
crackhash-1.0.1.dist-info/RECORD
crackhash-1.0.1.dist-info/WHEEL
crackhash-1.0.1.dist-info/entry_points.txt
crackhash-1.0.1.dist-info/metadata.json
crackhash-1.0.1.dist-info/top_level.txt
