Metadata-Version: 2.0
Name: crackhash
Version: 1.0.1
Summary: Crackhash is a tool that try to crack different types of hashes using free online services.
Home-page: https://github.com/5h4d0wb0y/crackhash
Author: 5h4d0wb0y
Author-email: 5h4d0wb0y@protonmail.com
License: GNU General Public License v3
Keywords: crackhash
Platform: UNKNOWN
Classifier: Development Status :: 5 - Production/Stable
Classifier: Intended Audience :: Developers
Classifier: License :: OSI Approved :: GNU General Public License v3 (GPLv3)
Classifier: Natural Language :: English
Classifier: Programming Language :: Python :: 2
Classifier: Programming Language :: Python :: 2.7
Classifier: Programming Language :: Python :: 3
Classifier: Programming Language :: Python :: 3.4
Classifier: Programming Language :: Python :: 3.5
Classifier: Programming Language :: Python :: 3.6
Classifier: Programming Language :: Python :: 3.7
Requires-Dist: Click (>=6.0)
Requires-Dist: selenium (>=3.141.0)
Requires-Dist: yaspin (>=0.14.0)
